LICENSE
mongometer/__init__.py
mongometer/aggregation.py
mongometer/executor.py
mongometer-0.1.0.dist-info/entry_points.txt
mongometer-0.1.0.dist-info/LICENSE
mongometer-0.1.0.dist-info/WHEEL
mongometer-0.1.0.dist-info/METADATA
mongometer-0.1.0.dist-info/RECORD
