Metadata-Version: 2.1
Name: mongometer
Version: 0.1.0
Summary: MongoDB aggregation pipeline performance checker
Home-page: https://github.com/roman-right/mongometer
License: MIT
Keywords: mongodb,python
Author: Roman
Author-email: roman-right@protonmail.com
Requires-Python: >=3.7,<4.0
Classifier: License :: OSI Approved :: MIT License
Classifier: Programming Language :: Python :: 3
Classifier: Programming Language :: Python :: 3.10
Classifier: Programming Language :: Python :: 3.7
Classifier: Programming Language :: Python :: 3.8
Classifier: Programming Language :: Python :: 3.9
Requires-Dist: click (>=8.1.3,<9.0.0)
Requires-Dist: dnspython (>=2.2.1,<3.0.0)
Requires-Dist: pymongo (>=4.1.1,<5.0.0)
Requires-Dist: rich (>=12.4.4,<13.0.0)
Project-URL: Repository, https://github.com/roman-right/mongometer
